flask_twitter/__init__.py
flask_twitter/twitter.py
Flask_Twitter-0.1.1.dist-info/LICENSE
Flask_Twitter-0.1.1.dist-info/METADATA
Flask_Twitter-0.1.1.dist-info/WHEEL
Flask_Twitter-0.1.1.dist-info/top_level.txt
Flask_Twitter-0.1.1.dist-info/RECORD
