Metadata-Version: 2.1
Name: Flask-Twitter
Version: 0.1.1
Summary: A simple twitter api v2 extension for flask
Home-page: https://github.com/MerleLiuKun/flask-twitter
Author: LiuKun
Author-email: merle.liukun@gmail.com
License: MIT
Platform: any
Classifier: Intended Audience :: Developers
Classifier: License :: OSI Approved :: MIT License
Classifier: Programming Language :: Python :: Implementation :: CPython
Classifier: Programming Language :: Python :: 3
Classifier: Topic :: Software Development :: Libraries :: Python Modules
Requires-Python: >=3.6
Requires-Dist: Flask
Requires-Dist: python-twitter-v2
